__init__.py
llm_app_test/__init__.py
llm_app_test/behavioral_assert/__init__.py
llm_app_test/behavioral_assert/behavioral_assert.py
llm_app_test/behavioral_assert/asserter_prompts/__init__.py
llm_app_test/behavioral_assert/asserter_prompts/asserter_prompt_configurator.py
llm_app_test/behavioral_assert/asserter_prompts/asserter_prompts.py
llm_app_test/behavioral_assert/behavioral_assert_config/__init__.py
llm_app_test/behavioral_assert/behavioral_assert_config/behavioral_assert_constants.py
llm_app_test/behavioral_assert/llm_config/__init__.py
llm_app_test/behavioral_assert/llm_config/llm_config.py
llm_app_test/behavioral_assert/llm_config/llm_factory.py
llm_app_test/behavioral_assert/llm_config/llm_provider_enum.py
llm_app_test/behavioral_assert/validation/__init__.py
llm_app_test/behavioral_assert/validation/behavioral_assert_input_validator.py
llm_app_test/behavioral_assert/validation/config_validator.py
llm_app_test/behavioral_assert/validation/config_validator_config.py
llm_app_test/behavioral_assert/validation/rate_limiter_input_validator.py
llm_app_test/behavioral_assert/validation/with_retry_config_validator.py
llm_app_test/exceptions/__init__.py
llm_app_test/exceptions/test_exceptions.py
llm_app_test/pytest_plugin/__init__.py
llm_app_test/pytest_plugin/plugin.py
llm_app_test/rate_limiter/__init__.py
llm_app_test/rate_limiter/rate_limiter_handler.py
llm_app_test/semantic_assert/__init__.py
llm_app_test/semantic_assert/semantic_assert.py
llm_app_test/with_retry/__init__.py
llm_app_test/with_retry/with_retry_config.py
llm_app_test-0.2.0b3.dist-info/LICENSE
llm_app_test-0.2.0b3.dist-info/METADATA
llm_app_test-0.2.0b3.dist-info/WHEEL
llm_app_test-0.2.0b3.dist-info/entry_points.txt
llm_app_test-0.2.0b3.dist-info/top_level.txt
llm_app_test-0.2.0b3.dist-info/RECORD
