Metadata-Version: 2.1
Name: llm_app_test
Version: 0.2.0b3
Summary: A behavioral testing library for LLM applications that allows developers to write natural language specifications for unit and integration tests. Validate LLM application behavior using plain English assertions in a simple assert(str, str) form factor.
Author-email: Morgan Lee <morganj.lee01@gmail.com>
License: MIT
Project-URL: Homepage, https://github.com/Shredmetal/llmtest
Project-URL: Documentation, https://shredmetal.github.io/llmtest/
Project-URL: Repository, https://github.com/Shredmetal/llmtest.git
Keywords: testing,llm,behavioral,pytest
Classifier: Development Status :: 4 - Beta
Classifier: Intended Audience :: Developers
Classifier: License :: OSI Approved :: MIT License
Classifier: Programming Language :: Python :: 3.10
Classifier: Programming Language :: Python :: 3.11
Classifier: Programming Language :: Python :: 3.12
Classifier: Topic :: Software Development :: Testing
Classifier: Framework :: Pytest
Requires-Python: >=3.10
License-File: LICENSE
Requires-Dist: langchain>=0.3.0
Requires-Dist: langchain-openai>=0.2.0
Requires-Dist: langchain-anthropic>=0.2.0
Requires-Dist: python-dotenv>=1.0.0
Requires-Dist: pytest>=7.0.0
Provides-Extra: dev
Requires-Dist: coverage; extra == "dev"
Requires-Dist: black; extra == "dev"
Requires-Dist: flake8; extra == "dev"
Requires-Dist: mkdocs>=1.5.0; extra == "dev"
Requires-Dist: mkdocs-material>=9.0.0; extra == "dev"
Requires-Dist: build; extra == "dev"
Requires-Dist: twine; extra == "dev"
Requires-Dist: codecov; extra == "dev"
